{
  "188": "FELIPE",
  "203": "FELIPE",
  "204": "FELIPE",
  "207": "FELIPE",
  "216": "FELIPE",
  "217": "FELIPE",
  "220": "HELIO",
  "221": "FELIPE",
  "238": "HELIO",
  "250": "RAFAEL",
  "254": "RAFAEL",
  "259": "ALTAMIRANDO",
  "269": "ALTAMIRANDO",
  "272": "FELIPE",
  "281": "FELIPE",
  "292": "FELIPE",
  "293": "FELIPE",
  "305": "WENDEL",
  "306": "WENDEL",
  "310": "HELIO",
  "311": "FELIPE",
  "317": "FELIPE",
  "325": "FELIPE",
  "331": "WENDEL",
  "344": "PEDROPAULO",
  "345": "BRUNO",
  "352": "FELIPE",
  "354": "HELIO",
  "359": "WENDEL",
  "377": "PEDROPAULO",
  "379": "PEDROPAULO",
  "380": "PEDROPAULO",
  "383": "FELIPE",
  "385": "WENDEL",
  "386": "FELIPE",
  "390": "BRUNO",
  "396": "FELIPE",
  "398": "FELIPE",
  "400": "PEDROPAULO",
  "401": "PEDROPAULO",
  "407": "PEDROPAULO",
  "409": "PEDROPAULO",
  "410": "PEDROPAULO",
  "413": "PEDROPAULO",
  "414": "BRUNO",
  "419": "PEDROPAULO",
  "420": "PEDROPAULO",
  "421": "PEDROPAULO",
  "424": "WENDEL",
  "426": "WENDEL",
  "429": "FELIPE",
  "440": "WENDEL",
  "451": "FELIPE",
  "457": "BRUNO",
  "458": "FELIPE",
  "462": "PEDROPAULO",
  "466": "PEDROPAULO",
  "479": "PEDROPAULO",
  "481": "PEDROPAULO",
  "488": "ANDRESSA",
  "493": "PEDROPAULO",
  "498": "HELIO",
  "499": "PEDROPAULO",
  "503": "PEDROPAULO",
  "504": "PEDROPAULO",
  "508": "FELIPE",
  "511": "PEDROPAULO",
  "514": "WENDEL",
  "518": "HELIO",
  "521": "HELIO",
  "529": "PEDROPAULO",
  "530": "FELIPE",
  "535": "HELIO",
  "540": "HELIO",
  "541": "HELIO",
  "574": "PEDROPAULO",
  "576": "PEDROPAULO",
  "582": "WENDEL",
  "586": "FELIPE",
  "589": "PEDROPAULO",
  "595": "WENDEL",
  "597": "WENDEL",
  "599": "WENDEL",
  "602": "WENDEL",
  "603": "WENDEL",
  "617": "PEDROPAULO",
  "627": "FELIPE",
  "629": "FELIPE",
  "636": "FELIPE",
  "641": "FELIPE",
  "642": "FELIPE",
  "647": "FELIPE",
  "656": "FELIPE",
  "660": "PEDROPAULO",
  "662": "PEDROPAULO",
  "667": "PEDROPAULO",
  "675": "PEDROPAULO",
  "681": "FELIPE",
  "682": "FELIPE",
  "684": "FELIPE",
  "686": "WENDEL",
  "690": "FELIPE",
  "691": "SUPRIMENTO",
  "697": "WENDEL",
  "701": "WENDEL",
  "702": "WENDEL",
  "703": "FELIPE",
  "704": "FELIPE",
  "705": "WENDEL",
  "706": "BRUNO",
  "707": "FELIPE",
  "709": "FELIPE",
  "712": "FELIPE",
  "716": "BRUNO",
  "719": "WENDEL",
  "720": "WENDEL",
  "724": "WENDEL",
  "729": "WENDEL",
  "730": "FELIPE",
  "733": "BRUNO",
  "738": "WENDEL",
  "745": "WENDEL",
  "748": "FELIPE",
  "749": "FELIPE",
  "750": "FELIPE",
  "751": "FELIPE",
  "752": "WENDEL",
  "755": "FELIPE",
  "758": "WENDEL",
  "766": "FELIPE",
  "767": "WENDEL",
  "772": "FELIPE",
  "774": "FELIPE",
  "775": "BRUNO",
  "778": "FELIPE",
  "779": "WENDEL",
  "790": "WENDEL",
  "791": "WENDEL",
  "792": "HELIO",
  "796": "FELIPE",
  "800": "FELIPE",
  "801": "BRUNO",
  "802": "BRUNO",
  "803": "WENDEL",
  "804": "BRUNO",
  "808": "FELIPE",
  "815": "FELIPE",
  "816": "FELIPE",
  "818": "ANDRESSA",
  "821": "FELIPE",
  "823": "ANDRESSA",
  "825": "FELIPE",
  "827": "RITA",
  "833": "WENDEL",
  "835": "RITA",
  "836": "WENDEL",
  "837": "ANDRESSA",
  "841": "WENDEL",
  "846": "RITA",
  "847": "WENDEL",
  "848": "BRUNO",
  "849": "BRUNO",
  "850": "BRUNO",
  "851": "RITA",
  "852": "RITA",
  "861": "BRUNO",
  "862": "BRUNO",
  "863": "BRUNO",
  "865": "FELIPE",
  "866": "BRUNO",
  "867": "RITA",
  "869": "WENDEL",
  "871": "WENDEL",
  "872": "WENDEL",
  "874": "FELIPE",
  "875": "WENDEL",
  "876": "RITA",
  "879": "RITA",
  "881": "RITA",
  "882": "WENDEL",
  "887": "RITA",
  "888": "WENDEL",
  "890": "WENDEL",
  "891": "SUPRIMENTO",
  "892": "BRUNO",
  "893": "SUPRIMENTO",
  "894": "BRUNO",
  "897": "WENDEL",
  "898": "RITA",
  "900": "FELIPE",
  "906": "RITA",
  "910": "FELIPE",
  "911": "WENDEL",
  "919": "WENDEL",
  "920": "RITA",
  "922": "WENDEL",
  "924": "ANDRESSA",
  "926": "RITA",
  "928": "RITA",
  "929": "ANDRESSA",
  "931": "BRUNO",
  "932": "RITA",
  "934": "ANDRESSA",
  "937": "ANDRESSA",
  "938": "BRUNO",
  "940": "HELIO",
  "941": "RITA",
  "942": "FELIPE",
  "944": "FELIPE",
  "946": "FELIPE",
  "947": "FELIPE",
  "948": "RITA",
  "949": "RITA",
  "950": "RITA",
  "951": "RITA",
  "952": "RITA",
  "953": "RITA",
  "955": "RITA",
  "956": "EMILSON",
  "957": "RITA",
  "958": "FELIPE",
  "959": "RITA",
  "960": "FELIPE",
  "961": "FELIPE",
  "964": "BRUNO",
  "966": "WENDEL",
  "967": "ANDRESSA",
  "968": "FELIPE",
  "969": "ANDRESSA",
  "971": "ANDRESSA",
  "972": "BRUNO",
  "975": "RITA",
  "977": "FELIPE",
  "979": "FELIPE",
  "980": "RITA",
  "981": "RITA",
  "984": "RITA",
  "987": "BRUNO",
  "989": "RITA",
  "990": "FELIPE",
  "992": "FELIPE",
  "993": "WENDEL",
  "994": "FELIPE",
  "998": "RITA",
  "1002": "RITA",
  "1004": "RITA",
  "1006": "RITA",
  "1007": "RITA",
  "1009": "WENDEL",
  "1011": "FELIPE",
  "1016": "BRUNO",
  "1017": "RITA",
  "1023": "RITA",
  "1024": "BRUNO",
  "1025": "BRUNO",
  "1030": "SANDRONEY",
  "1033": "BRUNO",
  "1037": "RITA",
  "1039": "RITA",
  "1041": "WENDEL",
  "1047": "BRUNO",
  "1048": "WENDEL",
  "1051": "RITA",
  "1053": "WENDEL",
  "1063": "SANDRONEY",
  "1064": "RITA",
  "1067": "BRUNO",
  "1068": "RITA",
  "1072": "RITA",
  "1077": "SANDRONEY",
  "1084": "BRUNO",
  "1085": "BRUNO",
  "1086": "RITA",
  "1087": "SANDRONEY",
  "1090": "SANDRONEY",
  "1091": "WENDEL",
  "1094": "RITA",
  "1095": "SANDRONEY",
  "1096": "SANDRONEY",
  "1113": "SANDRONEY",
  "1115": "WENDEL",
  "1118": "RITA",
  "1119": "RITA",
  "1121": "SANDRONEY",
  "1125": "WENDEL",
  "1128": "SANDRONEY",
  "1134": "SANDRONEY",
  "1136": "RITA",
  "1137": "RITA",
  "1141": "SANDRONEY",
  "1147": "WENDEL",
  "1148": "BRUNO",
  "1149": "RITA",
  "1160": "ISRAEL",
  "1161": "RITA",
  "1167": "ISRAEL",
  "1169": "WENDEL",
  "1172": "WENDEL",
  "1173": "WENDEL",
  "1174": "RITA",
  "1182": "ISRAEL",
  "1183": "ISRAEL",
  "1190": "ISRAEL",
  "1192": "ISRAEL",
  "1195": "RITA",
  "1212": "ISRAEL",
  "1213": "WENDEL",
  "1227": "ISRAEL",
  "1228": "RITA",
  "1233": "RITA",
  "1234": "RITA",
  "1237": "ISRAEL",
  "2178": "RITA",
  "2221": "RITA",
  "2222": "RITA",
  "2223": "RITA",
  "2225": "RITA",
  "2231": "RITA",
  "2232": "RITA",
  "2233": "RITA",
  "2235": "RITA",
  "2236": "SADJA",
  "2237": "RITA",
  "2238": "RITA",
  "2239": "BARBARA",
  "2242": "RITA",
  "2243": "RITA",
  "2244": "RITA",
  "2246": "MICHAEL",
  "2247": "RITA",
  "2248": "RITA",
  "2249": "BARBARA",
  "2251": "RITA",
  "2253": "RITA",
  "2254": "RITA",
  "2255": "RITA",
  "2258": "BARBARA",
  "2259": "RITA",
  "2260": "RITA",
  "2262": "BARBARA",
  "2266": "MICHAEL",
  "2268": "RITA",
  "2269": "RITA",
  "2270": "RITA",
  "2271": "RITA",
  "2272": "RITA",
  "2273": "RITA",
  "2274": "RITA",
  "2275": "RITA",
  "2276": "BARBARA",
  "2277": "JACKSON",
  "2278": "JACKSON",
  "2279": "BARBARA",
  "2280": "SADJA",
  "2281": "RITA",
  "2282": "MICHAEL",
  "2284": "RITA",
  "2285": "RITA",
  "2286": "RITA",
  "2290": "RITA",
  "2291": "RITA",
  "2292": "RITA",
  "2294": "MATEUS",
  "2295": "RITA",
  "2300": "SANDRONEY",
  "2302": "RITA",
  "2303": "RITA",
  "2306": "RITA",
  "2307": "SADJA",
  "2309": "RITA",
  "2310": "RITA",
  "2311": "RITA",
  "2323": "MATEUS",
  "2324": "RITA",
  "2325": "RITA",
  "2328": "RITA",
  "2330": "LUCAS",
  "2331": "RITA",
  "2332": "RITA",
  "2333": "RITA",
  "2336": "LUCAS",
  "2337": "SANDRONEY",
  "2338": "RITA",
  "2340": "RITA",
  "2341": "RITA",
  "2342": "LUCAS",
  "2343": "LUCAS",
  "2344": "RITA",
  "2345": "RITA",
  "2346": "LUCAS",
  "2348": "LUCAS",
  "2350": "LUCAS",
  "2351": "SADJA",
  "2355": "LUCAS",
  "2356": "RITA",
  "2359": "RITA",
  "2360": "MATEUS",
  "2361": "RITA",
  "2362": "RITA",
  "2363": "LUCAS",
  "2364": "RITA",
  "2365": "RITA",
  "2366": "LUCAS",
  "2367": "LUCAS",
  "2370": "MATEUS",
  "2371": "MATEUS",
  "2374": "LUCAS",
  "2375": "LUCAS",
  "2376": "LUCAS",
  "2378": "LUCAS",
  "2379": "LUCAS",
  "2380": "LUCAS",
  "2381": "RITA",
  "2382": "RITA",
  "2384": "LUCAS",
  "2387": "RITA",
  "2388": "RITA",
  "2389": "LUCAS",
  "2390": "RITA",
  "2392": "LUCAS",
  "2393": "LUCAS",
  "2394": "LUCAS",
  "2395": "MATEUS",
  "2396": "MATEUS",
  "2397": "JACKSON",
  "2398": "LUCAS",
  "2400": "LUCAS",
  "2401": "LUCAS",
  "2402": "LUCAS",
  "2404": "RITA",
  "2407": "RITA",
  "2409": "RITA",
  "2410": "RITA",
  "2411": "LUCAS",
  "2414": "LUCAS",
  "2415": "LUCAS",
  "2416": "LUCAS",
  "2419": "LUCAS",
  "2421": "JACKSON",
  "2422": "RITA",
  "2423": "RITA",
  "2425": "RITA",
  "2426": "RITA",
  "2427": "RITA",
  "2428": "LUCAS",
  "2429": "LUCAS",
  "2430": "LUCAS",
  "2431": "NETO",
  "2432": "MATEUS",
  "2433": "LUCAS",
  "2436": "LUCAS",
  "2437": "MATEUS",
  "2440": "MATEUS",
  "2443": "MATEUS",
  "2445": "LUCAS",
  "2446": "LUCAS",
  "2447": "NETO",
  "2450": "NETO",
  "2454": "MATEUS",
  "2455": "LUCAS",
  "2457": "LUCAS",
  "2458": "LUCAS",
  "2462": "MATEUS",
  "2463": "LUCAS",
  "2464": "MATEUS",
  "2465": "NETO",
  "2466": "LUCAS",
  "2469": "NETO",
  "2470": "NETO",
  "2471": "MATEUS",
  "2472": "LUCAS",
  "2475": "LUCAS",
  "2476": "LUCAS",
  "2477": "NETO",
  "2478": "MATEUS",
  "2483": "NETO",
  "2486": "MATEUS",
  "2488": "NETO",
  "2489": "LUCAS",
  "2491": "LUCAS",
  "2492": "LUCAS",
  "2493": "LUCAS",
  "2494": "NETO",
  "2496": "MATEUS",
  "2498": "JACKSON",
  "2502": "LUCAS",
  "2503": "LUCAS",
  "2504": "MATEUS",
  "2506": "LUCAS",
  "2509": "MATEUS",
  "2511": "NETO",
  "2512": "DAVI",
  "2520": "DAVI",
  "2522": "NETO",
  "2526": "NETO",
  "2527": "NETO",
  "2530": "LUCAS",
  "2531": "LUCAS",
  "2533": "LUCAS",
  "2534": "MATEUS",
  "2535": "LUCAS",
  "2536": "LUCAS",
  "2537": "MATEUS",
  "2538": "MATEUS",
  "2542": "LUCAS",
  "2545": "CLEUTON",
  "2547": "CLEUTON",
  "2548": "LUCAS",
  "2551": "LUCAS",
  "2552": "MATEUS",
  "2554": "LUCAS",
  "2557": "LUCAS",
  "2559": "LUCAS",
  "2574": "DAVI",
  "2582": "NETO",
  "2586": "MATEUS",
  "2604": "DAVI",
  "2609": "MATEUS",
  "2613": "LUCAS",
  "2621": "LUCAS",
  "2625": "CLEUTON",
  "2630": "DAVI",
  "2631": "LUCAS",
  "2636": "LUCAS",
  "2637": "MATEUS",
  "2648": "CLEUTON",
  "2704": "NETO",
  "2711": "LUCAS",
  "2719": "CLEUTON",
  "2746": "LUCAS",
  "2753": "DAVI",
  "2754": "LUCASARCANJO",
  "2759": "DANIELLY",
  "2762": "LUCAS",
  "2765": "DANIELLY",
  "2767": "CLEUTON",
  "2774": "LUCAS",
  "2777": "LUCAS",
  "2778": "CLEUTON",
  "2779": "NETO",
  "2780": "DAVI",
  "2782": "RITA",
  "2784": "LUCAS",
  "2785": "LUCAS",
  "2786": "LUCAS",
  "2792": "NETO",
  "2796": "LUCAS",
  "2797": "DAVI",
  "2804": "LUCAS",
  "2808": "DAVI",
  "2809": "DAVI",
  "2812": "RITA",
  "2814": "LUCAS",
  "2815": "DAVI",
  "2816": "LUCASARCANJO",
  "2818": "DANIELLY",
  "2819": "NETO",
  "2820": "DAVI",
  "2824": "LUCASARCANJO",
  "2826": "DANIELLY",
  "2827": "LUCAS",
  "2834": "DAVI",
  "2835": "DAVI",
  "2836": "JACKSON",
  "2837": "LUCAS",
  "2838": "RITA",
  "2841": "LUCAS",
  "2842": "NETO",
  "2845": "RITA",
  "2849": "JACKSON",
  "2850": "DAVI",
  "2851": "NETO",
  "2852": "NETO",
  "2853": "DAVI",
  "2854": "NETO",
  "2856": "RITA",
  "2857": "LUCAS",
  "2858": "DANIELLY",
  "2859": "SADJA",
  "2860": "LUCAS",
  "2861": "LUCAS",
  "2862": "DANIELLY",
  "2865": "LUCAS",
  "2866": "DAVI",
  "2868": "DAVI",
  "2869": "RITA",
  "2870": "NETO",
  "2876": "CLEUTON",
  "2878": "LUCAS",
  "2879": "LUCAS",
  "2880": "LUCAS",
  "2883": "DAVI",
  "2884": "LUCAS",
  "2886": "LUCAS",
  "2887": "LUCAS",
  "2889": "LUCAS",
  "2890": "LUCAS",
  "2892": "NETO",
  "2893": "DAVI",
  "2894": "DANIELLY",
  "2897": "RITA",
  "2898": "NETO",
  "2899": "RITA",
  "2900": "RITA",
  "2903": "RITA",
  "2905": "LUCAS",
  "2906": "LUCAS",
  "2913": "DAVI",
  "2916": "JACKSON",
  "2917": "DANIELLY",
  "2919": "NETO",
  "2920": "LUCAS",
  "2921": "LUCAS",
  "2924": "DAVI",
  "2926": "LUCAS",
  "2927": "RITA",
  "2932": "DAVI",
  "2933": "DAVI",
  "2934": "LUCAS",
  "2935": "NETO",
  "2937": "LUCAS",
  "2939": "LUCAS",
  "2940": "LUCAS",
  "2941": "LUCAS",
  "2942": "LUCAS",
  "2943": "LUCAS",
  "2944": "LUCAS",
  "2945": "LUCAS",
  "2946": "LUCAS",
  "2948": "LUCAS",
  "2949": "LUCAS",
  "2950": "LUCAS",
  "2952": "LUCAS",
  "2953": "LUCAS",
  "2955": "CLEUTON",
  "2957": "LUCAS",
  "2958": "LUCAS",
  "2959": "LUCAS",
  "2961": "CLEUTON",
  "2962": "ILLIEV",
  "2966": "CLEUTON",
  "2967": "NETO",
  "2969": "LUCAS",
  "2971": "LUCAS",
  "2972": "LUCAS",
  "2973": "LUCAS",
  "2974": "JONE",
  "2975": "DAVI",
  "2978": "JONE",
  "2986": "LUCAS",
  "2990": "LUCAS",
  "2991": "CLEUTON",
  "2993": "NETO",
  "2995": "LUCAS",
  "2999": "LUCAS",
  "3003": "NETO",
  "3004": "LUCAS",
  "3006": "LUCAS",
  "3008": "LUCAS",
  "3009": "LUCAS",
  "3013": "LUCAS",
  "3014": "LUCAS",
  "3015": "LUCAS",
  "3017": "JONE",
  "3019": "DAVI",
  "3020": "CLEUTON",
  "3023": "NETO",
  "3024": "DANIELLY",
  "3030": "DAVI",
  "3036": "CLEUTON",
  "3040": "LUCAS",
  "3043": "LUCAS",
  "3044": "LUCAS",
  "3045": "ILLIEV",
  "3046": "LUCAS",
  "3047": "LUCAS",
  "3048": "LUCAS",
  "3049": "LUCAS",
  "3050": "LUCAS",
  "3053": "DAVI",
  "3055": "RITA",
  "3056": "NETO",
  "3057": "LUCASARCANJO",
  "3058": "LUCAS",
  "3059": "LUCAS",
  "3060": "LUCAS",
  "3061": "LUCAS",
  "3062": "LUCAS",
  "3063": "LUCAS",
  "3065": "LUCAS",
  "3068": "JONE",
  "3071": "LUCASARCANJO",
  "3077": "LUCAS",
  "3078": "LUCAS",
  "3079": "LUCAS",
  "3082": "SADJA",
  "3086": "FRANCIBERNY",
  "3087": "RITA",
  "3088": "ILLIEV",
  "3090": "NETO",
  "3093": "SADJA",
  "3101": "RITA",
  "3102": "NETO",
  "3104": "SADJA",
  "3105": "DANIELLY",
  "3108": "LUCAS",
  "3109": "LUCAS",
  "3110": "LUCAS",
  "3111": "LUCAS",
  "3112": "NETO",
  "3114": "DAVI",
  "3115": "LUCAS",
  "3116": "LUCAS",
  "3117": "LUCAS",
  "3120": "CLEUTON",
  "3125": "DANIELLY",
  "3126": "NETO",
  "3127": "DANIELLY",
  "3128": "RITA",
  "3130": "RITA",
  "3131": "LUCASARCANJO",
  "3132": "RITA",
  "3133": "ILLIEV",
  "3135": "JONE",
  "3138": "LUCAS",
  "3140": "RITA",
  "3144": "ILLIEV",
  "3145": "ILLIEV",
  "3148": "RITA",
  "3162": "ILLIEV",
  "3163": "LUCAS",
  "3174": "LUCAS",
  "3180": "LUCAS",
  "3798": "VITOR",
  "4021": "FERNANDOBARROS",
  "4123": "LUCAS",
  "4163": "ALBERY",
  "4173": "ALBERY",
  "4192": "MATEUS",
  "4193": "ALBERY",
  "4195": "ALBERY",
  "4221": "MATEUS",
  "4227": "FRANCIBERNY",
  "4228": "NETO",
  "4231": "BARBARA",
  "4232": "BARBARA",
  "4234": "ALBERY",
  "4235": "LEONYS",
  "4236": "LUCAS",
  "4237": "LUCAS",
  "4242": "MATEUS",
  "4244": "CLEUTON",
  "4248": "FRANCIBERNY",
  "4249": "LEONYS",
  "4250": "GEAN",
  "4251": "MATEUS",
  "4252": "NETO",
  "4253": "LEONYS",
  "4254": "FRANCIBERNY",
  "4255": "ALBERY",
  "4257": "FRANCIBERNY",
  "4258": "MATEUS",
  "4259": "MATEUS",
  "4261": "LEONYS",
  "4264": "LUCAS",
  "4265": "LUCAS",
  "4267": "ALBERY",
  "4270": "ALBERY",
  "4271": "ALBERY",
  "4272": "MATEUS",
  "4273": "ALBERY",
  "4274": "LUCAS",
  "4275": "FRANCIBERNY",
  "4276": "MATEUS",
  "4278": "ALBERY",
  "4279": "ALBERY",
  "4280": "BARBARA",
  "4281": "LEONYS",
  "4282": "GEAN",
  "4283": "GEAN",
  "4284": "CLEUTON",
  "4285": "FRANCIBERNY",
  "4288": "ALBERY",
  "4289": "MATEUS",
  "4290": "JONE",
  "4291": "LEONYS",
  "4292": "MATEUS",
  "4293": "RITA",
  "4294": "MATEUS",
  "4295": "BARBARA",
  "4297": "NETO",
  "4299": "LUCAS",
  "4300": "LUCAS",
  "4301": "JONE",
  "4303": "JONE",
  "4304": "LUCAS",
  "4306": "LUCAS",
  "4307": "LUCAS",
  "4308": "LUCAS",
  "4309": "LUCAS",
  "4312": "LUCAS",
  "4313": "LUCAS",
  "4314": "ALBERY",
  "4318": "MATEUS",
  "4319": "JONE",
  "4321": "LUCAS",
  "4322": "LUCAS",
  "4323": "BARBARA",
  "4324": "BARBARA",
  "4329": "LEONYS",
  "4331": "FRANCIBERNY",
  "4332": "MATEUS",
  "4333": "ALBERY",
  "4335": "LEONYS",
  "4336": "NETO",
  "4338": "BARBARA",
  "4340": "ALBERY",
  "4341": "ALBERY",
  "4342": "LUCAS",
  "4344": "NETO",
  "4345": "JONE",
  "4346": "MATEUS",
  "4347": "LEONYS",
  "4350": "LUCAS",
  "4353": "LUCAS",
  "4354": "LUCAS",
  "4355": "MATEUS",
  "4356": "LEONYS",
  "4358": "LUCAS",
  "4363": "MOAB",
  "4368": "LEONYS",
  "4369": "MATEUS",
  "4371": "NETO",
  "4372": "MATEUS",
  "4373": "FRANCIBERNY",
  "4375": "MATEUS",
  "4377": "FRANCIBERNY",
  "4378": "NETO",
  "4380": "SADJA",
  "4381": "LUCAS",
  "4383": "LEONYS",
  "4384": "ALBERY",
  "4385": "LEONYS",
  "4386": "ALBERY",
  "4388": "LUCAS",
  "4389": "MATEUS",
  "4391": "LUCAS",
  "4392": "LUCAS",
  "4393": "ALBERY",
  "4394": "LEONYS",
  "4395": "FRANCIBERNY",
  "4399": "FRANCIBERNY",
  "4403": "JONE",
  "4408": "GEAN",
  "4411": "LUCAS",
  "4413": "LUCAS",
  "4415": "ALBERY",
  "4418": "LEONYS",
  "4419": "NETO",
  "4420": "ALBERY",
  "4424": "LUCAS",
  "4425": "LUCAS",
  "4427": "LUCAS",
  "4429": "LUCAS",
  "4435": "GEAN",
  "4436": "GEAN",
  "4437": "MATHEUS",
  "4440": "MATEUS",
  "4441": "MOAB",
  "4443": "ALBERY",
  "4445": "ALBERY",
  "4446": "NETO",
  "4448": "BARBARA",
  "4450": "BARBARA",
  "4451": "LUCAS",
  "4452": "LUCAS",
  "4453": "MATEUS",
  "4454": "LEONYS",
  "4456": "LUCAS",
  "4457": "LUCAS",
  "4460": "MATHEUS",
  "4461": "MATEUS",
  "4462": "FRANCIBERNY",
  "4464": "MATEUS",
  "4466": "MATEUS",
  "4469": "LUCAS",
  "4472": "ALBERY",
  "4475": "LEONYS",
  "4479": "JONE",
  "4480": "ALBERY",
  "4481": "NETO",
  "4485": "MATEUS",
  "4486": "MATHEUS",
  "4491": "FRANCIBERNY",
  "4496": "MATEUS",
  "4497": "SADJA",
  "4498": "LUCAS",
  "4501": "FRANCIBERNY",
  "4503": "MATEUS",
  "4504": "MATEUS",
  "4506": "ALBERY",
  "4507": "MATHEUS",
  "4509": "LUCAS",
  "4510": "LUCAS",
  "4512": "LUCAS",
  "4513": "LEONYS",
  "4515": "JONE",
  "4519": "FRANCIBERNY",
  "4520": "FRANCIBERNY",
  "4521": "MATEUS",
  "4522": "JONE",
  "4523": "FRANCIBERNY",
  "4525": "LEONYS",
  "4527": "ALBERY",
  "4530": "LUCAS",
  "4531": "LUCAS",
  "4533": "GEAN",
  "4539": "BARBARA",
  "4544": "MOAB",
  "4548": "LUCAS",
  "4549": "FRANCIBERNY",
  "4550": "ALBERY",
  "4552": "MATEUS",
  "4554": "MATEUS",
  "4555": "NETO",
  "4557": "LUCAS",
  "4559": "LUCAS",
  "4563": "JONE",
  "4564": "NETO",
  "4568": "MOAB",
  "4574": "GEAN",
  "4578": "MATHEUS",
  "4579": "ALBERY",
  "4583": "LUCAS",
  "4584": "JONE",
  "4585": "LUCAS",
  "4596": "MATHEUS",
  "4601": "NETO",
  "4608": "ALBERY",
  "6803": "GABRIEL",
  "9301": "WALISSON",
  "9373": "ARTUR",
  "9382": "ARTUR",
  "9385": "ELMARA",
  "9390": "WALISSON",
  "9393": "LEVI",
  "9410": "LEONARDO",
  "9413": "ARTUR",
  "9415": "GUSTAVO",
  "9416": "GUSTAVO",
  "9417": "GUSTAVO",
  "9418": "GUSTAVO",
  "9420": "GUSTAVO",
  "9424": "ARTUR",
  "9426": "ARTUR",
  "9428": "ARTUR",
  "9430": "EWERTON",
  "9431": "WALISSON",
  "9432": "GUSTAVO",
  "9433": "ARTUR",
  "9434": "ARTUR",
  "9436": "LEVI",
  "9440": "LEVI",
  "9441": "LEONARDO",
  "9442": "LEONARDO",
  "9443": "ARTUR",
  "9446": "MAURICIO",
  "9447": "LEVI",
  "9448": "LEVI",
  "9449": "LEVI",
  "9450": "LEVI",
  "9451": "LEVI",
  "9452": "LEONARDO",
  "9456": "WALISSON",
  "9457": "GUSTAVOAGUIAR",
  "9458": "ARTUR",
  "9459": "ARTUR",
  "9461": "ARTUR",
  "9463": "ERANILDO",
  "9464": "ERANILDO",
  "9465": "ERANILDO",
  "9474": "WALISSON",
  "9476": "WALISSON",
  "9477": "WALISSON",
  "9479": "WALISSON",
  "9493": "ARTUR",
  "9495": "LEVI",
  "9497": "GEAN",
  "9500": "LEVI",
  "9503": "EWERTON",
  "9504": "WALISSON",
  "9507": "ARTUR",
  "9513": "WALISSON",
  "9515": "MAURICIO",
  "9530": "ARTUR",
  "9533": "LEVI",
  "9534": "ARTUR",
  "9535": "ARTUR",
  "9540": "ARTUR",
  "9541": "ARTUR",
  "9542": "EWERTON",
  "9548": "WALISSON",
  "9551": "GUSTAVOAGUIAR",
  "9552": "LEVI",
  "9553": "LEVI",
  "9554": "LEVI",
  "9555": "LEVI",
  "9556": "LEVI",
  "9558": "GEAN",
  "9559": "LEONARDO",
  "9560": "MAURICIO",
  "9561": "WALISSON",
  "9567": "WALISSON",
  "9568": "WALISSON",
  "9571": "JOAO",
  "9574": "JOAO",
  "9575": "EWERTON",
  "9576": "GUSTAVOAGUIAR",
  "9578": "REGIS",
  "9579": "REGIS",
  "9580": "GUSTAVO",
  "9583": "FRANCILEUDO",
  "9584": "REGIS",
  "9586": "JOAO",
  "9589": "VALERIA",
  "9593": "GEAN",
  "9597": "MAURICIO",
  "9598": "JOAO",
  "9601": "GUSTAVO",
  "9610": "GUSTAVO",
  "9611": "WALISSON",
  "9612": "WALISSON",
  "9613": "GUSTAVO",
  "9615": "GUSTAVO",
  "9617": "GUSTAVO",
  "9620": "JOAO",
  "9621": "JOAO",
  "9629": "MAURICIO",
  "9631": "GEAN",
  "9632": "GUSTAVOAGUIAR",
  "9634": "SERGIO",
  "9642": "GUSTAVOAGUIAR",
  "9645": "GUSTAVO",
  "9646": "GUSTAVO",
  "9648": "GUSTAVO",
  "9671": "GUSTAVO",
  "9672": "GUSTAVO",
  "9675": "WALISSON",
  "9691": "GUSTAVO",
  "9694": "GUSTAVO",
  "9695": "MAURICIO",
  "9706": "EWERTON",
  "9711": "GUSTAVO",
  "9713": "GUSTAVO",
  "9715": "LUISPAULO",
  "9716": "LUISPAULO",
  "9718": "LUISPAULO",
  "9721": "HERBERTT",
  "9722": "HERBERTT",
  "9723": "HERBERTT",
  "9729": "HERBERTT",
  "9778": "JACKSON",
  "9779": "GUSTAVO",
  "9782": "WESLLEY",
  "9783": "ERICAMACIEL",
  "9785": "MAURICIO",
  "9790": "HERBERTT",
  "9795": "LUISPAULO",
  "9804": "GUSTAVO",
  "9805": "GUSTAVO",
  "9806": "GUSTAVO",
  "9807": "REGIS",
  "9808": "GUSTAVO",
  "9812": "WALISSON",
  "9816": "ERICA",
  "9817": "JACKSON",
  "9824": "YURI",
  "9827": "JOAO",
  "9833": "LUISPAULO",
  "9834": "GUSTAVO",
  "9835": "LUISPAULO",
  "9837": "HERBERTT",
  "9838": "LUISPAULO",
  "9845": "JACKSON",
  "9846": "LUISPAULO",
  "9847": "MAURICIO",
  "9849": "WALISSON",
  "9850": "WALISSON",
  "9855": "MAURICIO",
  "9856": "JOAO",
  "9860": "YURI",
  "9861": "YURI",
  "9862": "MAURICIO",
  "9865": "MAURICIO",
  "9869": "YURI",
  "9874": "GUSTAVOAGUIAR",
  "9875": "YURI",
  "9876": "WALISSON",
  "9877": "WALISSON",
  "9879": "EWERTON",
  "9880": "YURI",
  "9881": "GUSTAVO",
  "9886": "GUSTAVO",
  "9890": "ERICA",
  "9891": "GUSTAVO",
  "9895": "YURI",
  "9896": "YURI",
  "9897": "YURI",
  "9899": "GUSTAVOAGUIAR",
  "9900": "YURI",
  "9906": "GUSTAVO",
  "9907": "GUSTAVO",
  "9912": "YURI",
  "9914": "HERBERTT",
  "9916": "ESAU",
  "9922": "YURI",
  "9923": "WESLLEY",
  "9924": "YURI",
  "9926": "YURI",
  "9928": "JACKSON",
  "9931": "WALISSON",
  "9933": "GUSTAVO",
  "9934": "WALISSON",
  "9936": "MAURICIO",
  "9943": "LUISPAULO",
  "9949": "YURI",
  "9963": "GEAN",
  "9969": "YURI",
  "9973": "YURI",
  "9974": "YURI",
  "9975": "YURI",
  "9976": "GUSTAVO",
  "9978": "GUSTAVO",
  "9981": "YURI",
  "9983": "YURI",
  "9985": "GUSTAVOAGUIAR",
  "9991": "MAURICIO",
  "9992": "GUSTAVO",
  "9994": "HERBERTT",
  "9996": "EDUARDO",
  "9997": "GUSTAVO",
  "9998": "GUSTAVO",
  "9999": "LUISPAULO",
  "10004": "GUSTAVO",
  "10009": "LUISPAULO",
  "10011": "LUISPAULO",
  "10012": "MAURICIO",
  "10013": "YURI",
  "10014": "HERBERTT",
  "10017": "YURI"
}